white_generator/__init__.py
white_generator/__main__.py
white_generator/cli.py
white_generator/db.py
white_generator/generation.py
white_generator/io.py
white_generator/io_test.py
white_generator/logger.py
white_generator/main.py
white_generator/text.py
white_generator/text_test.py
white_generator/types.py
white_generator/types_test.py
white_generator-2.0.0.dist-info/LICENSE.txt
white_generator-2.0.0.dist-info/METADATA
white_generator-2.0.0.dist-info/WHEEL
white_generator-2.0.0.dist-info/entry_points.txt
white_generator-2.0.0.dist-info/top_level.txt
white_generator-2.0.0.dist-info/RECORD
