Metadata-Version: 2.1
Name: white-generator
Version: 2.0.0
Summary: Utility for a generation of memes
Author-email: thewizardplusplus <thewizardplusplus@yandex.ru>
License: MIT License
Project-URL: Homepage, https://github.com/thewizardplusplus/white-generator
Requires-Python: <4.0.0,>=3.10.12
License-File: LICENSE.txt
Requires-Dist: termcolor (<3.0.0,>=2.4.0)
Requires-Dist: pillow (<11.0.0,>=10.3.0)
